cpplib_pybind.cpython-39-x86_64-linux-gnu.so
cpplib-1.0.5.dist-info/WHEEL
cpplib-1.0.5.dist-info/LICENSE
cpplib-1.0.5.dist-info/RECORD
cpplib-1.0.5.dist-info/top_level.txt
cpplib-1.0.5.dist-info/METADATA
cpplib/__init__.py
cpplib/helper.py
cpplib.libs/libgomp-f7e03b3e.so.1.0.0
