Metadata-Version: 2.1
Name: cpplib
Version: 1.0.5
Summary: Test CPPLib integration
Home-page: https://github.com/JeremyBYU/cpp-pybind-skel
Author: Jeremy Castagno
Author-email: jeremybyu@gmail.com
License: MIT
Platform: UNKNOWN
Requires-Dist: numpy (>=1.15.0)
